CHANGELOG.rst
MANIFEST.in
README.rst
setup.cfg
setup.py
bb_pytest/__init__.py
bb_pytest/step.py
bb_pytest.egg-info/PKG-INFO
bb_pytest.egg-info/SOURCES.txt
bb_pytest.egg-info/dependency_links.txt
bb_pytest.egg-info/entry_points.txt
bb_pytest.egg-info/not-zip-safe
bb_pytest.egg-info/top_level.txt
bb_pytest/test/__init__.py
bb_pytest/test/fixture.problems
bb_pytest/test/fixture.py
bb_pytest/test/fixture.stdout
bb_pytest/test/fixture_failures.problems
bb_pytest/test/fixture_failures.stdout
bb_pytest/test/test_pytest.py