Metadata-Version: 1.0
Name: bb-pytest
Version: 0.2
Summary: Buildbot step for py.test.
Home-page: https://github.com/russell/bb-pytest
Author: Russell Sim
Author-email: russell.sim@gmail.com
License: GPL
Platform: UNKNOWN
